mastercardblockchain/__init__.py
mastercardblockchain/block.py
mastercardblockchain/node.py
mastercardblockchain/resourceconfig.py
mastercardblockchain/send.py
mastercardblockchain/status.py
mastercardblockchain/transactionentry.py
mastercard_blockchain-19.8.0.dist-info/LICENSE
mastercard_blockchain-19.8.0.dist-info/METADATA
mastercard_blockchain-19.8.0.dist-info/WHEEL
mastercard_blockchain-19.8.0.dist-info/top_level.txt
mastercard_blockchain-19.8.0.dist-info/RECORD
